uvinert/__init__.py
uvinert/inert.py
uvinert-0.6.2.dev2.dist-info/METADATA
uvinert-0.6.2.dev2.dist-info/WHEEL
uvinert-0.6.2.dev2.dist-info/licenses/LICENSE
uvinert-0.6.2.dev2.dist-info/RECORD
