Metadata-Version: 2.4
Name: uvinert
Version: 0.6.2.dev2
Summary: Custom inert build backend for UV monorepo
License-File: LICENSE
